jsane/__init__.py
jsane/traversable.py
jsane/wrapper.py
jsane-0.1.2.dist-info/DESCRIPTION.rst
jsane-0.1.2.dist-info/METADATA
jsane-0.1.2.dist-info/RECORD
jsane-0.1.2.dist-info/WHEEL
jsane-0.1.2.dist-info/metadata.json
jsane-0.1.2.dist-info/pbr.json
jsane-0.1.2.dist-info/top_level.txt
