Metadata-Version: 1.1
Name: jsane
Version: 0.1.2
Summary: A saner way to parse JSON.
Home-page: https://github.com/skorokithakis/jsane/
Author: Stavros Korokithakis
Author-email: hi@stavros.io
License: MIT
Platform: UNKNOWN
Classifier: License :: OSI Approved :: MIT License
Classifier: Programming Language :: Python
Classifier: Programming Language :: Python :: 2.7
Classifier: Programming Language :: Python :: 3.3
Classifier: Programming Language :: Python :: 3.4
Classifier: Programming Language :: Python :: 3.5
Classifier: Programming Language :: Python :: 3.6
Classifier: Topic :: Software Development :: Libraries :: Python Modules
